testpackageJdka/__init__.py
testpackageJdka/hello.py
testpackageJdka/hi.py
testpackageJdka-0.0.7.dist-info/METADATA
testpackageJdka-0.0.7.dist-info/WHEEL
testpackageJdka-0.0.7.dist-info/top_level.txt
testpackageJdka-0.0.7.dist-info/RECORD
